SEMIS/priority_encoder_4to2.v
// priority_encoder_4to2_with_tb.v
`timescale 1ns/1ps

module priority_encoder_4to2 (
    input [3:0] in,       // 4-bit input
    output reg [1:0] out, // 2-bit encoded output
    output reg valid      // Indicates if any input is high
);
    always @(*) begin
        valid = 1'b1;
        casex (in)
            4'b1xxx: out = 2'b11; // Highest priority
            4'b01xx: out = 2'b10;
            4'b001x: out = 2'b01;
            4'b0001: out = 2'b00;
            default: begin
                out = 2'b00;
                valid = 1'b0;
            end
        endcase
    end
endmodule

// Testbench for Priority Encoder
module tb_priority_encoder;
    reg [3:0] in;
    wire [1:0] out;
    wire valid;

    // Instantiate the DUT (Device Under Test)
    priority_encoder_4to2 uut (
        .in(in),
        .out(out),
        .valid(valid)
    );

    initial begin
        // Setup VCD file for GTKWave
        $dumpfile("priority_encoder.vcd"); // VCD file for GTKWave
        $dumpvars(0, tb_priority_encoder); // Dump all vars in the testbench

        // Apply test inputs
        in = 4'b0000; #10;
        in = 4'b0001; #10;
        in = 4'b0010; #10;
        in = 4'b0011; #10;
        in = 4'b0100; #10;
        in = 4'b0101; #10;
        in = 4'b0110; #10;
        in = 4'b0111; #10;
        in = 4'b1000; #10;
        in = 4'b1001; #10;
        in = 4'b1111; #10;

        // End simulation
        $finish;
    end
endmodule

SEMIS/priority_encoder.vcd
$date
	Mon May 19 00:12:01 2025
$end
$version
	Icarus Verilog
$end
$timescale
	1ps
$end
$scope module tb_priority_encoder $end
$var wire 1 ! valid $end
$var wire 2 " out [1:0] $end
$var reg 4 # in [3:0] $end
$scope module uut $end
$var wire 4 $ in [3:0] $end
$var reg 2 % out [1:0] $end
$var reg 1 ! valid $end
$upscope $end
$upscope $end
$enddefinitions $end
#0
$dumpvars
b0 %
b0 $
b0 #
b0 "
0!
$end
#10000
1!
b1 #
b1 $
#20000
b1 "
b1 %
b10 #
b10 $
#30000
b11 #
b11 $
#40000
b10 "
b10 %
b100 #
b100 $
#50000
b101 #
b101 $
#60000
b110 #
b110 $
#70000
b111 #
b111 $
#80000
b11 "
b11 %
b1000 #
b1000 $
#90000
b1001 #
b1001 $
#100000
b1111 #
b1111 $
