FINALS/4bitUp.v
module counter4 (
    input wire clk,        // Clock input
    input wire nReset,     // Active-low asynchronous reset
    input wire nE,          // Active-low enable
    input wire cntby2,      // Increment-by-2 enable
    output reg [3:0] count  // 4-bit counter output
);

  // Asynchronous reset:  The counter is reset regardless of the clock.
  always @(posedge clk or negedge nReset) begin
    if (~nReset) begin
      count <= 4'b0000;  // Reset the counter to 0
    end else if (~nE) begin // Check enable: Only count if nE is low
      if (cntby2) begin
        count <= count + 2'b10; // Increment by 2
      end else begin
        count <= count + 1'b01; // Increment by 1
      end
    end 
  end

endmodule

// Testbench Module
module counter4_tb;

  // Declare signals for the testbench
  reg clk;
  reg nReset;
  reg nE;
  reg cntby2;
  wire [3:0] count;

  // Instantiate the counter4 module
  counter4 dut (
    .clk(clk),
    .nReset(nReset),
    .nE(nE),
    .cntby2(cntby2),
    .count(count)
  );

  // Generate a clock signal
  initial begin
    clk = 0;
    forever #5 clk = ~clk;  // Toggle clock every 5 time units (period = 10)
  end

  // Apply reset, enable, and cntby2 signals
  initial begin
    nReset = 0; // Assert reset 
    nE     = 1;
    cntby2 = 0;
    #10;
    nReset = 1; // Deassert reset
    #20;      //after 20 ns reset is deasserted.

    nE = 0;     // Enable the counter
    #40;
    cntby2 = 1;  // Test increment by 2
    #40;
    cntby2 = 0;  // Test increment by 1
    #40;
    nE = 1;     // Disable the counter
    #20;
    nReset = 0;  //test reset again.
    #10;
    nReset = 1;
    #20;
    $finish;
  end

  // Dump signals for waveform viewing in GTKWave
  initial begin
    $dumpfile("counter4.vcd");
    $dumpvars(0, counter4_tb);
  end

endmodule

FINALS/counter4.vcd
$date
	Mon May 19 00:55:19 2025
$end
$version
	Icarus Verilog
$end
$timescale
	1s
$end
$scope module counter4_tb $end
$var wire 4 ! count [3:0] $end
$var reg 1 " clk $end
$var reg 1 # cntby2 $end
$var reg 1 $ nE $end
$var reg 1 % nReset $end
$scope module dut $end
$var wire 1 " clk $end
$var wire 1 # cntby2 $end
$var wire 1 $ nE $end
$var wire 1 % nReset $end
$var reg 4 & count [3:0] $end
$upscope $end
$upscope $end
$enddefinitions $end
#0
$dumpvars
b0 &
0%
1$
0#
0"
b0 !
$end
#5
1"
#10
0"
1%
#15
1"
#20
0"
#25
1"
#30
0"
0$
#35
b1 !
b1 &
1"
#40
0"
#45
b10 !
b10 &
1"
#50
0"
#55
b11 !
b11 &
1"
#60
0"
#65
b100 !
b100 &
1"
#70
0"
1#
#75
b110 !
b110 &
1"
#80
0"
#85
b1000 !
b1000 &
1"
#90
0"
#95
b1010 !
b1010 &
1"
#100
0"
#105
b1100 !
b1100 &
1"
#110
0"
0#
#115
b1101 !
b1101 &
1"
#120
0"
#125
b1110 !
b1110 &
1"
#130
0"
#135
b1111 !
b1111 &
1"
#140
0"
#145
b0 !
b0 &
1"
#150
0"
1$
#155
1"
#160
0"
#165
1"
#170
0"
0%
#175
1"
#180
0"
1%
