FINALS/JKFlipFlops.v
// JK Flip-Flop module
module jk_flip_flop (
    input clk,     // Clock input
    input j,       // J input
    input k,       // K input
    input reset_n, // Active-low reset
    output reg q,  // Q output
    output reg q_bar // Q_bar output
);

    // Use an always block to define sequential behavior
    always @(posedge clk or negedge reset_n) begin
        if (~reset_n) begin // If reset_n is low, reset the flip-flop
            q <= 1'b0;
            q_bar <= 1'b1;
        end else begin
            case ({j, k})
                2'b00: begin // J=0, K=0: No change
                    q <= q;
                    q_bar <= q_bar;
                end
                2'b01: begin // J=0, K=1: Reset
                    q <= 1'b0;
                    q_bar <= 1'b1;
                end
                2'b10: begin // J=1, K=0: Set
                    q <= 1'b1;
                    q_bar <= 1'b0;
                end
                2'b11: begin // J=1, K=1: Toggle
                    q <= ~q;
                    q_bar <= ~q_bar;
                end
            endcase
        end
    end

endmodule

// Testbench module
module jk_flip_flop_tb;
    // Declare signals for the testbench
    reg clk;
    reg j;
    reg k;
    reg reset_n;
    wire q;
    wire q_bar;

    // Instantiate the JK flip-flop
    jk_flip_flop uut (
        .clk(clk),
        .j(j),
        .k(k),
        .reset_n(reset_n),
        .q(q),
        .q_bar(q_bar)
    );

    // Generate a clock signal
    always #5 clk = ~clk; // Toggle clock every 5 time units

    // Initialize signals and apply stimulus
    initial begin
        // Initialize all signals
        clk = 1'b0;
        j = 1'b0;
        k = 1'b0;
        reset_n = 1'b0; // Start with reset active

        // Dump waveforms for GTKWave
        $dumpfile("jk_flip_flop.vcd");  // Specify the VCD file name
        $dumpvars(0, jk_flip_flop_tb); // Dump all signals in the testbench

        // Apply a reset pulse
        #10 reset_n = 1'b1; // Deactivate reset after 10 time units

        // Apply different J and K combinations
        #20 j = 1'b0; k = 1'b0; // No change
        #20 j = 1'b0; k = 1'b1; // Reset
        #20 j = 1'b1; k = 1'b0; // Set
        #20 j = 1'b1; k = 1'b1; // Toggle
        #20 j = 1'b1; k = 1'b1; // Toggle again
        #20 j = 1'b0; k = 1'b0;
        #20 j = 1'b1; k = 1'b0;
        #20 j = 1'b0; k = 1'b1;
        #20 j = 1'b1; k = 1'b1;

        #20 $finish; // End the simulation
    end

    //optional display
    initial begin
        $monitor("Time = %0t, clk = %b, j = %b, k = %b, reset_n = %b, q = %b, q_bar = %b",
                 $time, clk, j, k, reset_n, q, q_bar);
    end

endmodule

FINALS/jk_flip_flop.vcd
$date
	Mon May 19 00:25:07 2025
$end
$version
	Icarus Verilog
$end
$timescale
	1s
$end
$scope module jk_flip_flop_tb $end
$var wire 1 ! q_bar $end
$var wire 1 " q $end
$var reg 1 # clk $end
$var reg 1 $ j $end
$var reg 1 % k $end
$var reg 1 & reset_n $end
$scope module uut $end
$var wire 1 # clk $end
$var wire 1 $ j $end
$var wire 1 % k $end
$var wire 1 & reset_n $end
$var reg 1 " q $end
$var reg 1 ! q_bar $end
$upscope $end
$upscope $end
$enddefinitions $end
#0
$dumpvars
0&
0%
0$
0#
0"
1!
$end
#5
1#
#10
0#
1&
#15
1#
#20
0#
#25
1#
#30
0#
#35
1#
#40
0#
#45
1#
#50
0#
1%
#55
1#
#60
0#
#65
1#
#70
0#
0%
1$
#75
0!
1"
1#
#80
0#
#85
1#
#90
0#
1%
#95
1!
0"
1#
#100
0#
#105
0!
1"
1#
#110
0#
#115
1!
0"
1#
#120
0#
#125
0!
1"
1#
#130
0#
0%
0$
#135
1#
#140
0#
#145
1#
#150
0#
1$
#155
1#
#160
0#
#165
1#
#170
0#
1%
0$
#175
1!
0"
1#
#180
0#
#185
1#
#190
0#
1$
#195
0!
1"
1#
#200
0#
#205
1!
0"
1#
